LICENSE
MANIFEST.in
README.md
setup.cfg
setup.py
tap_onfleet/__init__.py
tap_onfleet/context.py
tap_onfleet/discover.py
tap_onfleet/onfleet.py
tap_onfleet/streams.py
tap_onfleet/sync.py
tap_onfleet.egg-info/PKG-INFO
tap_onfleet.egg-info/SOURCES.txt
tap_onfleet.egg-info/dependency_links.txt
tap_onfleet.egg-info/entry_points.txt
tap_onfleet.egg-info/requires.txt
tap_onfleet.egg-info/top_level.txt
tap_onfleet/schemas/administrators.json
tap_onfleet/schemas/hubs.json
tap_onfleet/schemas/organizations.json
tap_onfleet/schemas/schema-fixtures.json
tap_onfleet/schemas/tasks.json
tap_onfleet/schemas/teams.json
tap_onfleet/schemas/workers.json