Metadata-Version: 1.1
Name: tap-onfleet
Version: 1.0.0
Summary: Singer.io tap for extracting data from the onfleet API
Home-page: http://github.com/lambtron/tap-onfleet
Author: Stitch
Author-email: UNKNOWN
License: UNKNOWN
Platform: UNKNOWN
Classifier: Programming Language :: Python :: 3 :: Only
